clearspot/__init__.py
clearspot/ortho.py
clearspot-0.2.dist-info/METADATA
clearspot-0.2.dist-info/WHEEL
clearspot-0.2.dist-info/entry_points.txt
clearspot-0.2.dist-info/top_level.txt
clearspot-0.2.dist-info/RECORD
