Metadata-Version: 2.1
Name: clearspot
Version: 0.2
Summary: UNKNOWN
Home-page: UNKNOWN
License: UNKNOWN
Platform: UNKNOWN
Requires-Dist: docker
Requires-Dist: pyodm
